CHANGELOG
LICENSE
MANIFEST.in
README.rst
requirements.txt
setup.py
densli.egg-info/PKG-INFO
densli.egg-info/SOURCES.txt
densli.egg-info/dependency_links.txt
densli.egg-info/entry_points.txt
densli.egg-info/requires.txt
densli.egg-info/top_level.txt
serverdensity/__init__.py
serverdensity/densli/__init__.py
serverdensity/densli/app.py
serverdensity/densli/config.json
serverdensity/densli/version.txt