Metadata-Version: 1.0
Name: densli
Version: 1.0.1
Summary: CLI tool for working with the ServerDensity.com API
Home-page: https://github.com/serverdensity/densli
Author: Wes Mason
Author-email: wes@serverdensity.com
License: BSD
Platform: UNKNOWN
